{
  "+79099549035": {
    "cookies": [
      {
        "comment": null,
        "comment_url": null,
        "discard": false,
        "domain": ".login.vk.com",
        "domain_initial_dot": false,
        "domain_specified": true,
        "expires": null,
        "name": "p",
        "path": "/",
        "path_specified": true,
        "port": null,
        "port_specified": false,
        "rest": {
          "HttpOnly": null
        },
        "rfc2109": false,
        "secure": true,
        "value": "vk1.a.QyQfesn0z06f6PAAxxQNTzYcZ5-sVtvDSQUi2Ya9UIB_wjaPkShpV_JaZ6TPpE2RaSDxRj3SykF8IIyQsbE-wpLmPTgewvDBHQ9lXcipP3jewZQVGihN4FvAh2FPNTC6-bJ4-ckYuM3yCVsUYQskW79e_JCN7x-xlsKm_jlVH0A",
        "version": 0
      },
      {
        "comment": null,
        "comment_url": null,
        "discard": false,
        "domain": ".login.vk.com",
        "domain_initial_dot": false,
        "domain_specified": true,
        "expires": null,
        "name": "s",
        "path": "/",
        "path_specified": true,
        "port": null,
        "port_specified": false,
        "rest": {
          "HttpOnly": null
        },
        "rfc2109": false,
        "secure": true,
        "value": "1",
        "version": 0
      },
      {
        "comment": null,
        "comment_url": null,
        "discard": false,
        "domain": ".vk.com",
        "domain_initial_dot": true,
        "domain_specified": true,
        "expires": null,
        "name": "remixlang",
        "path": "/",
        "path_specified": true,
        "port": null,
        "port_specified": false,
        "rest": {},
        "rfc2109": false,
        "secure": false,
        "value": "0",
        "version": 0
      },
      {
        "comment": null,
        "comment_url": null,
        "discard": false,
        "domain": ".vk.com",
        "domain_initial_dot": true,
        "domain_specified": true,
        "expires": null,
        "name": "remixsid",
        "path": "/",
        "path_specified": true,
        "port": null,
        "port_specified": false,
        "rest": {
          "HttpOnly": null
        },
        "rfc2109": false,
        "secure": true,
        "value": "1_-d7ryfxB8RxSkV03KwGr_8XdOpyrxK1VUbflawnkTaKQlEtgvsySmu_cWV-HKBbxuVeN-AKlU9eM6VaDeqHD-A",
        "version": 0
      },
      {
        "comment": null,
        "comment_url": null,
        "discard": false,
        "domain": ".vk.com",
        "domain_initial_dot": true,
        "domain_specified": true,
        "expires": null,
        "name": "remixstid",
        "path": "/",
        "path_specified": true,
        "port": null,
        "port_specified": false,
        "rest": {},
        "rfc2109": false,
        "secure": true,
        "value": "1964439735_sJZoldJZAKxqE86VKTBxUW4Qznc0z3cuJZhRnfowe5P",
        "version": 0
      },
      {
        "comment": null,
        "comment_url": null,
        "discard": false,
        "domain": ".vk.com",
        "domain_initial_dot": true,
        "domain_specified": true,
        "expires": null,
        "name": "remixstlid",
        "path": "/",
        "path_specified": true,
        "port": null,
        "port_specified": false,
        "rest": {},
        "rfc2109": false,
        "secure": true,
        "value": "9051752346353047188_70hFZhXnp2S22ZmCVSLWcVoru4c0ERhvaOY1HdxeIhT",
        "version": 0
      },
      {
        "comment": null,
        "comment_url": null,
        "discard": false,
        "domain": ".vk.com",
        "domain_initial_dot": true,
        "domain_specified": true,
        "expires": null,
        "name": "remixua",
        "path": "/",
        "path_specified": true,
        "port": null,
        "port_specified": false,
        "rest": {},
        "rfc2109": false,
        "secure": true,
        "value": "41%7C-1%7C310%7C3683197456",
        "version": 0
      },
      {
        "comment": null,
        "comment_url": null,
        "discard": false,
        "domain": "login.vk.com",
        "domain_initial_dot": false,
        "domain_specified": false,
        "expires": null,
        "name": "remixluas2",
        "path": "/",
        "path_specified": true,
        "port": null,
        "port_specified": false,
        "rest": {
          "HttpOnly": null
        },
        "rfc2109": false,
        "secure": true,
        "value": "NWJmOWU1MmY0NDY0ZDJlOTZlN2JhNjg2",
        "version": 0
      },
      {
        "comment": null,
        "comment_url": null,
        "discard": false,
        "domain": "vk.com",
        "domain_initial_dot": false,
        "domain_specified": false,
        "expires": null,
        "name": "remixluas2",
        "path": "/",
        "path_specified": true,
        "port": null,
        "port_specified": false,
        "rest": {
          "HttpOnly": null
        },
        "rfc2109": false,
        "secure": true,
        "value": "NWUyMzllZjcwYTBhYTlhOWZmZmE1ZTQy",
        "version": 0
      },
      {
        "comment": null,
        "comment_url": null,
        "discard": false,
        "domain": "vk.com",
        "domain_initial_dot": false,
        "domain_specified": false,
        "expires": null,
        "name": "remixnsid",
        "path": "/",
        "path_specified": true,
        "port": null,
        "port_specified": false,
        "rest": {
          "HttpOnly": null
        },
        "rfc2109": false,
        "secure": true,
        "value": "vk1.a.qMLkvDmcWXybJHA6wvT6LQr6oxyY2f3wdcQD8zjwNjGQFrJzDVgALOsRSFhfznzxnYGas1DlJR44geqowAOy0exdOSxaSGC2nHurg8_-lynmVD8MzVbsqqolbJvBlpAZTuuzH5jMufKAM57-d6RKflHmc5E9InTijc5Kavz1xMLCTy2O3l0H_C8aPrhnwk4s",
        "version": 0
      }
    ],
    "token": {
      "app2685278": {
        "scope_140492255": {
          "access_token": "vk1.a.Idj48On4X4inAAx9ME-l2NWcf5VIauOCLEKM0_X49v7U4vEBwY2vrn2xxkJMwS4g2intYqlWSnOlesJiSXD3yxjjxDLLPsArxe6dJ6YljN8lgkjRwPeRU6D_KpqyCOZQLfJgj0c2JLZDalA0mbL7ZGHiEWiC2kD6X6246wH7O9nDeYiqaz21HlQEhL0EBZdU",
          "expires_in": "0",
          "user_id": "661706483"
        }
      }
    }
  },
  "+79582537602": {
    "cookies": [
      {
        "comment": null,
        "comment_url": null,
        "discard": false,
        "domain": ".login.vk.com",
        "domain_initial_dot": false,
        "domain_specified": true,
        "expires": null,
        "name": "p",
        "path": "/",
        "path_specified": true,
        "port": null,
        "port_specified": false,
        "rest": {
          "HttpOnly": null
        },
        "rfc2109": false,
        "secure": true,
        "value": "vk1.a.HzgLE1xCeDeIcVAb0TFKxSaME2LvnkzAy4SFvSy4vhtuy1XKXCD43KNvELQdNL7jY5Y8XsK2jw-Vf4pqGARFGq9wlrhzo_pLcIdZhnBob9uqzJnG5Abkuhb9fum9N0s_eixVDTaGG8kFvZQbraRp3KHDyiKTzi-ggFR6MxAq94k",
        "version": 0
      },
      {
        "comment": null,
        "comment_url": null,
        "discard": false,
        "domain": ".login.vk.com",
        "domain_initial_dot": false,
        "domain_specified": true,
        "expires": null,
        "name": "s",
        "path": "/",
        "path_specified": true,
        "port": null,
        "port_specified": false,
        "rest": {
          "HttpOnly": null
        },
        "rfc2109": false,
        "secure": true,
        "value": "1",
        "version": 0
      },
      {
        "comment": null,
        "comment_url": null,
        "discard": false,
        "domain": ".vk.com",
        "domain_initial_dot": true,
        "domain_specified": true,
        "expires": null,
        "name": "remixlang",
        "path": "/",
        "path_specified": true,
        "port": null,
        "port_specified": false,
        "rest": {},
        "rfc2109": false,
        "secure": false,
        "value": "0",
        "version": 0
      },
      {
        "comment": null,
        "comment_url": null,
        "discard": false,
        "domain": ".vk.com",
        "domain_initial_dot": true,
        "domain_specified": true,
        "expires": null,
        "name": "remixlgck",
        "path": "/",
        "path_specified": true,
        "port": null,
        "port_specified": false,
        "rest": {
          "HttpOnly": null
        },
        "rfc2109": false,
        "secure": true,
        "value": "894d8fe61daa269dd0",
        "version": 0
      },
      {
        "comment": null,
        "comment_url": null,
        "discard": false,
        "domain": ".vk.com",
        "domain_initial_dot": true,
        "domain_specified": true,
        "expires": null,
        "name": "remixsid",
        "path": "/",
        "path_specified": true,
        "port": null,
        "port_specified": false,
        "rest": {
          "HttpOnly": null
        },
        "rfc2109": false,
        "secure": true,
        "value": "1_rNc6XXwY9ZAK1CLVX4gCIegFzMr7XtDOvKLN0awvv4z1jMIXowkF_LrPxuVZHnhKpwLiD94NcZ8_0i9IZoMCVQ",
        "version": 0
      },
      {
        "comment": null,
        "comment_url": null,
        "discard": false,
        "domain": ".vk.com",
        "domain_initial_dot": true,
        "domain_specified": true,
        "expires": null,
        "name": "remixstid",
        "path": "/",
        "path_specified": true,
        "port": null,
        "port_specified": false,
        "rest": {},
        "rfc2109": false,
        "secure": true,
        "value": "1790495579_LeSfj3yOe4JkzrwFBOvkoszyl5eSinzfYqoXiPMmA9w",
        "version": 0
      },
      {
        "comment": null,
        "comment_url": null,
        "discard": false,
        "domain": ".vk.com",
        "domain_initial_dot": true,
        "domain_specified": true,
        "expires": null,
        "name": "remixstlid",
        "path": "/",
        "path_specified": true,
        "port": null,
        "port_specified": false,
        "rest": {},
        "rfc2109": false,
        "secure": true,
        "value": "9110727591024715256_oa0TKG0XMpgoQPwD1cZMxXV5Neh7Zst2rrhlWdspxz0",
        "version": 0
      },
      {
        "comment": null,
        "comment_url": null,
        "discard": false,
        "domain": ".vk.com",
        "domain_initial_dot": true,
        "domain_specified": true,
        "expires": null,
        "name": "remixua",
        "path": "/",
        "path_specified": true,
        "port": null,
        "port_specified": false,
        "rest": {},
        "rfc2109": false,
        "secure": true,
        "value": "41%7C-1%7C310%7C3683197456",
        "version": 0
      },
      {
        "comment": null,
        "comment_url": null,
        "discard": false,
        "domain": "login.vk.com",
        "domain_initial_dot": false,
        "domain_specified": false,
        "expires": null,
        "name": "remixluas2",
        "path": "/",
        "path_specified": true,
        "port": null,
        "port_specified": false,
        "rest": {
          "HttpOnly": null
        },
        "rfc2109": false,
        "secure": true,
        "value": "YmUzNDg3Yzk5OGI4NWFiMmQ4MDViNjc4",
        "version": 0
      },
      {
        "comment": null,
        "comment_url": null,
        "discard": false,
        "domain": "vk.com",
        "domain_initial_dot": false,
        "domain_specified": false,
        "expires": null,
        "name": "remixluas2",
        "path": "/",
        "path_specified": true,
        "port": null,
        "port_specified": false,
        "rest": {
          "HttpOnly": null
        },
        "rfc2109": false,
        "secure": true,
        "value": "ZGM4ZDliNWRjN2NhMThiNWQzMDU4NjAy",
        "version": 0
      },
      {
        "comment": null,
        "comment_url": null,
        "discard": false,
        "domain": "vk.com",
        "domain_initial_dot": false,
        "domain_specified": false,
        "expires": null,
        "name": "remixnsid",
        "path": "/",
        "path_specified": true,
        "port": null,
        "port_specified": false,
        "rest": {
          "HttpOnly": null
        },
        "rfc2109": false,
        "secure": true,
        "value": "vk1.a.xDtbrHyba-ZixMjHUVNIC15lFeBhRph__vsfVxW11IJMgjeCbPi_Ooy0unoY0sMcaa0PDI9V4h3vOhziHTk6sEokqokvxBXkRTM2QvO-3UB5H_UH3M45q74dd1GfPMcdaZwWk252zdsNn07dTNv6tdi7hoOX3tZWIjFf_PrsYIgS2pu6FFJ2KUY_BZk7LaSM",
        "version": 0
      }
    ],
    "token": {
      "app2685278": {
        "scope_140492255": {
          "access_token": "vk1.a.3uad64pA_ix8yk06A0yXJmKt9Snt5SXV57m0Xdym0p6HKluXb-40UOn04GDH05c5niljz3ehdCqnsw64MvqopuphoMSVz-7_4IQ74u-LSAS-oKcKboA5ldJgDBG34Bh_1ieBgWIZ9rGX6GvJNDQtvVFhFG48P4jC-4V3CPzZoWBils9MmCKCmgzCj04e1ZLqRJUr2R0A_kWTWdvpG13_kA",
          "expires_in": "0",
          "user_id": "723231031"
        }
      }
    }
  },
  "375295415732": {
    "cookies": [
      {
        "comment": null,
        "comment_url": null,
        "discard": false,
        "domain": ".vk.com",
        "domain_initial_dot": true,
        "domain_specified": true,
        "expires": null,
        "name": "remixlang",
        "path": "/",
        "path_specified": true,
        "port": null,
        "port_specified": false,
        "rest": {},
        "rfc2109": false,
        "secure": false,
        "value": "0",
        "version": 0
      },
      {
        "comment": null,
        "comment_url": null,
        "discard": false,
        "domain": ".vk.com",
        "domain_initial_dot": true,
        "domain_specified": true,
        "expires": null,
        "name": "remixstlid",
        "path": "/",
        "path_specified": true,
        "port": null,
        "port_specified": false,
        "rest": {},
        "rfc2109": false,
        "secure": true,
        "value": "9098907391060622557_EyFN1KqXthojoo8EkMbEYVv5Nbx5wy7Y9zADSzzQL4s",
        "version": 0
      },
      {
        "comment": null,
        "comment_url": null,
        "discard": false,
        "domain": ".vk.com",
        "domain_initial_dot": true,
        "domain_specified": true,
        "expires": null,
        "name": "remixua",
        "path": "/",
        "path_specified": true,
        "port": null,
        "port_specified": false,
        "rest": {},
        "rfc2109": false,
        "secure": true,
        "value": "41%7C-1%7C310%7C3683197456",
        "version": 0
      },
      {
        "comment": null,
        "comment_url": null,
        "discard": false,
        "domain": ".vk.com",
        "domain_initial_dot": true,
        "domain_specified": true,
        "expires": null,
        "name": "remixstid",
        "path": "/",
        "path_specified": true,
        "port": null,
        "port_specified": false,
        "rest": {},
        "rfc2109": false,
        "secure": true,
        "value": "84886694_SNSYWlbd8UVZuRf0zDt2sdNg5XOl5tzKPtx2FknJUkc",
        "version": 0
      },
      {
        "comment": null,
        "comment_url": null,
        "discard": false,
        "domain": ".vk.com",
        "domain_initial_dot": true,
        "domain_specified": true,
        "expires": null,
        "name": "remixsid",
        "path": "/",
        "path_specified": true,
        "port": null,
        "port_specified": false,
        "rest": {
          "HttpOnly": null
        },
        "rfc2109": false,
        "secure": true,
        "value": "1_8-5UHM1wI-AMP0Fe18q2-kRib-FX9suO8Tlfb2uADV_pSXGNX0s2swCDosw_-UtB7puRNN3dpHn3t1rUGzGJng",
        "version": 0
      },
      {
        "comment": null,
        "comment_url": null,
        "discard": false,
        "domain": ".vk.com",
        "domain_initial_dot": true,
        "domain_specified": true,
        "expires": null,
        "name": "remixst",
        "path": "/",
        "path_specified": true,
        "port": null,
        "port_specified": false,
        "rest": {},
        "rfc2109": false,
        "secure": true,
        "value": "82add8f0e078d50ab0",
        "version": 0
      },
      {
        "comment": null,
        "comment_url": null,
        "discard": false,
        "domain": ".login.vk.com",
        "domain_initial_dot": false,
        "domain_specified": true,
        "expires": null,
        "name": "s",
        "path": "/",
        "path_specified": true,
        "port": null,
        "port_specified": false,
        "rest": {
          "HttpOnly": null
        },
        "rfc2109": false,
        "secure": true,
        "value": "1",
        "version": 0
      },
      {
        "comment": null,
        "comment_url": null,
        "discard": false,
        "domain": ".login.vk.com",
        "domain_initial_dot": false,
        "domain_specified": true,
        "expires": null,
        "name": "p",
        "path": "/",
        "path_specified": true,
        "port": null,
        "port_specified": false,
        "rest": {
          "HttpOnly": null
        },
        "rfc2109": false,
        "secure": true,
        "value": "vk1.a.DSlq9swUodPZbKllBg2AudbNgU6cdDCSFwE0gjwSVU8fes_eeXg0-4G0BAjRxjG5DhUA4As22MSvH4rd73PVz6dexRzXJCgRCk81vJSQiBywUX1ctzZLYSFkCB1GUUlT_I_33iVMYQDKQb8HLTA9Z_c7fTOI_3c3LaFrzsXONFg",
        "version": 0
      },
      {
        "comment": null,
        "comment_url": null,
        "discard": false,
        "domain": "vk.com",
        "domain_initial_dot": false,
        "domain_specified": false,
        "expires": null,
        "name": "remixnsid",
        "path": "/",
        "path_specified": true,
        "port": null,
        "port_specified": false,
        "rest": {
          "HttpOnly": null
        },
        "rfc2109": false,
        "secure": true,
        "value": "vk1.a.3blaUsd2SwGvF7eIdn1s2uP1-djW25C3ZnmHXz5gsttOG4umYfnyGIWHUKyQwyhrk_A3j1Of0-dYykPKGikqzvpGa8_8RfJRfR6UVrHmsoX7xLs-DBkFRd2PG-t8cYglfs67yf5WoFntxJiPOBEde8W5ca1BrS7_wxZ61kVQZfmQ3LGGt-Q7WMEvRuvJ3d6r",
        "version": 0
      },
      {
        "comment": null,
        "comment_url": null,
        "discard": false,
        "domain": "vk.com",
        "domain_initial_dot": false,
        "domain_specified": false,
        "expires": null,
        "name": "remixluas2",
        "path": "/",
        "path_specified": true,
        "port": null,
        "port_specified": false,
        "rest": {
          "HttpOnly": null
        },
        "rfc2109": false,
        "secure": true,
        "value": "MWY4MDI1MzIyOWE5NGFjODJmNTUzMmFl",
        "version": 0
      }
    ],
    "token": {
      "app2685278": {
        "scope_140492255": {
          "access_token": "vk1.a.yTajGgT_f_WJ_j8kiLCQWsR9Yj4LHhiAVQ-hCd4SRf5XhlHKitXWf-0HNRyae7TWOHHep8fWnC_l9X4xYW1aK6AGYVdEM0AXlja9oEm4qN8il1FahHIn0qxH9yPSVMXDK-ZhMaPrChYamchqInx778MKdQsG14TMQJW0SbH6Zrr1kBugeEaLqQSpNp042ecpewn0ug5QVnduHCNPq1t4sA",
          "expires_in": "0",
          "user_id": "764085002"
        }
      }
    }
  },
  "380672331845": {
    "cookies": [
      {
        "comment": null,
        "comment_url": null,
        "discard": false,
        "domain": ".vk.com",
        "domain_initial_dot": true,
        "domain_specified": true,
        "expires": null,
        "name": "remixlang",
        "path": "/",
        "path_specified": true,
        "port": null,
        "port_specified": false,
        "rest": {},
        "rfc2109": false,
        "secure": false,
        "value": "0",
        "version": 0
      },
      {
        "comment": null,
        "comment_url": null,
        "discard": false,
        "domain": ".vk.com",
        "domain_initial_dot": true,
        "domain_specified": true,
        "expires": null,
        "name": "remixstlid",
        "path": "/",
        "path_specified": true,
        "port": null,
        "port_specified": false,
        "rest": {},
        "rfc2109": false,
        "secure": true,
        "value": "9075122756085484941_1zCBjN8MpK4RgF4J2zccI9K3bKA8Rjp0EIfDaN3quvg",
        "version": 0
      },
      {
        "comment": null,
        "comment_url": null,
        "discard": false,
        "domain": ".vk.com",
        "domain_initial_dot": true,
        "domain_specified": true,
        "expires": null,
        "name": "remixua",
        "path": "/",
        "path_specified": true,
        "port": null,
        "port_specified": false,
        "rest": {},
        "rfc2109": false,
        "secure": true,
        "value": "41%7C-1%7C310%7C3683197456",
        "version": 0
      },
      {
        "comment": null,
        "comment_url": null,
        "discard": false,
        "domain": ".vk.com",
        "domain_initial_dot": true,
        "domain_specified": true,
        "expires": null,
        "name": "remixstid",
        "path": "/",
        "path_specified": true,
        "port": null,
        "port_specified": false,
        "rest": {},
        "rfc2109": false,
        "secure": true,
        "value": "1949380840_YHzRory8fm2nwTmjoymVcVLkovFoZsVJZfIlDuugkPD",
        "version": 0
      },
      {
        "comment": null,
        "comment_url": null,
        "discard": false,
        "domain": ".vk.com",
        "domain_initial_dot": true,
        "domain_specified": true,
        "expires": null,
        "name": "remixsid",
        "path": "/",
        "path_specified": true,
        "port": null,
        "port_specified": false,
        "rest": {
          "HttpOnly": null
        },
        "rfc2109": false,
        "secure": true,
        "value": "1_6rWkKeEVjzMwwDmfWTxfuM6qU3lB-jC7LR0kF6wiUYa94sEZInDYe_Gnz9oaDluQl6syVZU0-lgxhMgKkOE1RA",
        "version": 0
      },
      {
        "comment": null,
        "comment_url": null,
        "discard": false,
        "domain": ".login.vk.com",
        "domain_initial_dot": false,
        "domain_specified": true,
        "expires": null,
        "name": "s",
        "path": "/",
        "path_specified": true,
        "port": null,
        "port_specified": false,
        "rest": {
          "HttpOnly": null
        },
        "rfc2109": false,
        "secure": true,
        "value": "1",
        "version": 0
      },
      {
        "comment": null,
        "comment_url": null,
        "discard": false,
        "domain": ".login.vk.com",
        "domain_initial_dot": false,
        "domain_specified": true,
        "expires": null,
        "name": "p",
        "path": "/",
        "path_specified": true,
        "port": null,
        "port_specified": false,
        "rest": {
          "HttpOnly": null
        },
        "rfc2109": false,
        "secure": true,
        "value": "vk1.a.BBJf8mkVHCJcgcZ-YAlTYYZztp7-xeO3AD18VLfmjQ3ICezI8FfqRcjJ6qVWyNN-GhctshVGr5nnw-Lq8YYJ4NzjRqKRAwRtN-W1CzAPU-hLfEBElrIebCcbxJh7sBIDeBAEuKSV3dmUFxdIF73PsgwA1fvUV1wZ7oX-JYX1pwM",
        "version": 0
      },
      {
        "comment": null,
        "comment_url": null,
        "discard": false,
        "domain": "login.vk.com",
        "domain_initial_dot": false,
        "domain_specified": false,
        "expires": null,
        "name": "remixluas2",
        "path": "/",
        "path_specified": true,
        "port": null,
        "port_specified": false,
        "rest": {
          "HttpOnly": null
        },
        "rfc2109": false,
        "secure": true,
        "value": "N2VkZjY2Mzc0YTRkZGEyM2MxZGM3OWQz",
        "version": 0
      },
      {
        "comment": null,
        "comment_url": null,
        "discard": false,
        "domain": "vk.com",
        "domain_initial_dot": false,
        "domain_specified": false,
        "expires": null,
        "name": "remixnsid",
        "path": "/",
        "path_specified": true,
        "port": null,
        "port_specified": false,
        "rest": {
          "HttpOnly": null
        },
        "rfc2109": false,
        "secure": true,
        "value": "vk1.a.Y-L3gUzKLG9CHDdLh-ugDX2SZC9PnP2bUA6cHX02ZLdSBHfY6jGcw9UGxLtUGQQ8ETSrNFmPVpupw5JNdMdZbFaS6cvEyoqp6SUlVw1YAltt1zUDyOVVJNQKWzxDjWYhknxO2KD2yCKCu6pOrw20srcbiMvPBUX6GO_3eFG-GijFUreXYfCo96uDFswO5DY4",
        "version": 0
      },
      {
        "comment": null,
        "comment_url": null,
        "discard": false,
        "domain": "vk.com",
        "domain_initial_dot": false,
        "domain_specified": false,
        "expires": null,
        "name": "remixluas2",
        "path": "/",
        "path_specified": true,
        "port": null,
        "port_specified": false,
        "rest": {
          "HttpOnly": null
        },
        "rfc2109": false,
        "secure": true,
        "value": "MTMyYmQzMjRmNzUxYzgyNzEyZGNjODcz",
        "version": 0
      }
    ],
    "token": {
      "app2685278": {
        "scope_140492255": {
          "access_token": "vk1.a.wS98ZL9xvOdoy3RGKkc8at-cR18nrqwQ15MhsYRjn4H9JVF8garnNgztVoGkBM04R1rMa0r1fKrjmG0SQXiaulCbLgiDKnNMXGDSvxyYvxjNn2TozsVEfcVp27fHxD_aJIYjLLBuQb83_ewjwoUPcHqauErdX6g8_D16_AQajV3sk6zj5mKRDgfzWknNaRHtY1hJ-ef2GqEsk4Emnmx6gg",
          "expires_in": "0",
          "user_id": "409782954"
        }
      }
    }
  },
  "79582537602": {
    "cookies": [
      {
        "comment": null,
        "comment_url": null,
        "discard": false,
        "domain": ".vk.com",
        "domain_initial_dot": true,
        "domain_specified": true,
        "expires": null,
        "name": "remixlang",
        "path": "/",
        "path_specified": true,
        "port": null,
        "port_specified": false,
        "rest": {},
        "rfc2109": false,
        "secure": false,
        "value": "0",
        "version": 0
      },
      {
        "comment": null,
        "comment_url": null,
        "discard": false,
        "domain": ".vk.com",
        "domain_initial_dot": true,
        "domain_specified": true,
        "expires": null,
        "name": "remixstlid",
        "path": "/",
        "path_specified": true,
        "port": null,
        "port_specified": false,
        "rest": {},
        "rfc2109": false,
        "secure": true,
        "value": "9088774292788433193_bOVTZg4WRxYAcJmC2LBkvdoswttbzKaeKj63L0Gsias",
        "version": 0
      },
      {
        "comment": null,
        "comment_url": null,
        "discard": false,
        "domain": ".vk.com",
        "domain_initial_dot": true,
        "domain_specified": true,
        "expires": null,
        "name": "remixlgck",
        "path": "/",
        "path_specified": true,
        "port": null,
        "port_specified": false,
        "rest": {
          "HttpOnly": null
        },
        "rfc2109": false,
        "secure": true,
        "value": "e7822043d5dee2cc0d",
        "version": 0
      },
      {
        "comment": null,
        "comment_url": null,
        "discard": false,
        "domain": ".vk.com",
        "domain_initial_dot": true,
        "domain_specified": true,
        "expires": null,
        "name": "remixua",
        "path": "/",
        "path_specified": true,
        "port": null,
        "port_specified": false,
        "rest": {},
        "rfc2109": false,
        "secure": true,
        "value": "41%7C-1%7C310%7C3683197456",
        "version": 0
      },
      {
        "comment": null,
        "comment_url": null,
        "discard": false,
        "domain": ".vk.com",
        "domain_initial_dot": true,
        "domain_specified": true,
        "expires": null,
        "name": "remixstid",
        "path": "/",
        "path_specified": true,
        "port": null,
        "port_specified": false,
        "rest": {},
        "rfc2109": false,
        "secure": true,
        "value": "1547198968_YPPpUAPTfXWPAZp4ZloE4Z27FeXwzVfrykACfqqsTHT",
        "version": 0
      },
      {
        "comment": null,
        "comment_url": null,
        "discard": false,
        "domain": ".vk.com",
        "domain_initial_dot": true,
        "domain_specified": true,
        "expires": null,
        "name": "remixsid",
        "path": "/",
        "path_specified": true,
        "port": null,
        "port_specified": false,
        "rest": {
          "HttpOnly": null
        },
        "rfc2109": false,
        "secure": true,
        "value": "1_SsX4UumiFMDaexxsNRYTDkriTE2ThVXwd68KgUUc8MwkFf9MnMz4-dIjFsL_XPWAVS_3uozCH6DfXE880gz2Gg",
        "version": 0
      },
      {
        "comment": null,
        "comment_url": null,
        "discard": false,
        "domain": ".login.vk.com",
        "domain_initial_dot": false,
        "domain_specified": true,
        "expires": null,
        "name": "s",
        "path": "/",
        "path_specified": true,
        "port": null,
        "port_specified": false,
        "rest": {
          "HttpOnly": null
        },
        "rfc2109": false,
        "secure": true,
        "value": "1",
        "version": 0
      },
      {
        "comment": null,
        "comment_url": null,
        "discard": false,
        "domain": ".login.vk.com",
        "domain_initial_dot": false,
        "domain_specified": true,
        "expires": null,
        "name": "p",
        "path": "/",
        "path_specified": true,
        "port": null,
        "port_specified": false,
        "rest": {
          "HttpOnly": null
        },
        "rfc2109": false,
        "secure": true,
        "value": "vk1.a.saPmf0y6BPDdVdkcAnjr-p3oDExrq_1avDPNu5ckdlL2nLH6IwOrJqrQLrNWCs7jVqkZ2SIulyJv4TSLHzTWXgP-zR7pADL54auhjW-1N9sANNIk5YxCf4wbeOK-CYQOV8WjMl-uqPH_2zA93D0G6UgGlTYMTKYXFCL0eEdvfU0",
        "version": 0
      },
      {
        "comment": null,
        "comment_url": null,
        "discard": false,
        "domain": "login.vk.com",
        "domain_initial_dot": false,
        "domain_specified": false,
        "expires": null,
        "name": "remixluas2",
        "path": "/",
        "path_specified": true,
        "port": null,
        "port_specified": false,
        "rest": {
          "HttpOnly": null
        },
        "rfc2109": false,
        "secure": true,
        "value": "MGViMTY0OGY1ZTgzNWY4NzEyOWEyODg4",
        "version": 0
      },
      {
        "comment": null,
        "comment_url": null,
        "discard": false,
        "domain": "vk.com",
        "domain_initial_dot": false,
        "domain_specified": false,
        "expires": null,
        "name": "remixnsid",
        "path": "/",
        "path_specified": true,
        "port": null,
        "port_specified": false,
        "rest": {
          "HttpOnly": null
        },
        "rfc2109": false,
        "secure": true,
        "value": "vk1.a.o0PmrIXByRQdUNERy0rQuxw_XacMIu4UxwdEZn5941DEjsPt8q0SKVfmfMtClheMBmvktIXdeIfBMvVPmG0AROzXxufGqUiWkZnTkfFfnz4DFi6tkANN4XXFTMgeBNnwLMOP6JkKYr4gAf3noNOe7vQFzx40gh6RIIJrY5mIR7rQcE_tKysQsBa8WzWUJz34",
        "version": 0
      },
      {
        "comment": null,
        "comment_url": null,
        "discard": false,
        "domain": "vk.com",
        "domain_initial_dot": false,
        "domain_specified": false,
        "expires": null,
        "name": "remixluas2",
        "path": "/",
        "path_specified": true,
        "port": null,
        "port_specified": false,
        "rest": {
          "HttpOnly": null
        },
        "rfc2109": false,
        "secure": true,
        "value": "NDQ3OTllZGUzOGM0YTM3ZTY0Y2U4M2Iw",
        "version": 0
      }
    ],
    "token": {
      "app2685278": {
        "scope_140492255": {
          "access_token": "vk1.a.6dmLm9dipoFIvsxJWZhgCq1DFwTIYhnemZ820y-YuqKGkOt7JMkkHS7pIQzl-7uWgtxcUXOlAgfjL3_1tdwsVP3BzNz3weviQbx7Lx3Bmr8aCQbqXinZOvN0XSjVsxfQUwAty5udgdKDfi3OuJpJ_Ty-5HZepIlNKnuoAdQIkCJK8soKaWMtupWDkyhFvtMeW7pwQF2Pl4oGaOtp3PaQjA",
          "expires_in": "0",
          "user_id": "723231031"
        }
      }
    }
  }
}